Metadata-Version: 2.1
Name: calculator-ncal
Version: 0.0.1
Summary: this is a trial package used for calculation.
Home-page: UNKNOWN
Author: Neha Pappachan
Author-email: nehapappachan@gmail.com
License: MIT
Platform: UNKNOWN
License-File: licence.txt
